redis_entraid/__init__.py
redis_entraid/cred_provider.py
redis_entraid/identity_provider.py
vivi_redis_entraid-1.0.0.dist-info/licenses/LICENSE
vivi_redis_entraid-1.0.0.dist-info/METADATA
vivi_redis_entraid-1.0.0.dist-info/WHEEL
vivi_redis_entraid-1.0.0.dist-info/top_level.txt
vivi_redis_entraid-1.0.0.dist-info/RECORD
