Metadata-Version: 2.4
Name: vivi-redis-entraid
Version: 1.0.0
Summary: This is a fork of the original repo redis-py-entraid with support for azure-identity~=1.21.0
Author-email: "Kinetic Solutions Group." <mgarcia@ksgai.com>
Requires-Python: >=3.8
License-File: LICENSE
Requires-Dist: redis==6.2.0
Requires-Dist: PyJWT~=2.9.0
Requires-Dist: msal~=1.31.0
Requires-Dist: azure-identity~=1.21.0
Dynamic: license-file
